README.rst
setup.py
tinfo/__init__.py
tinfo.egg-info/PKG-INFO
tinfo.egg-info/SOURCES.txt
tinfo.egg-info/dependency_links.txt
tinfo.egg-info/entry_points.txt
tinfo.egg-info/top_level.txt