Metadata-Version: 1.0
Name: tinfo
Version: 1.0.0
Summary: Console extension to tmux
Home-page: https://github.com/richo/tinfo
Author: Richo Healey
Author-email: richo@psych0tik.net
License: MIT
Platform: UNKNOWN
